oteltest/__init__.py
oteltest/main.py
oteltest/private.py
oteltest/telemetry.py
oteltest/version.py
oteltest/sink/__init__.py
oteltest/sink/handler.py
oteltest/sink/main.py
oteltest/sink/private.py
oteltest/viz/__init__.py
oteltest/viz/main.py
oteltest/viz/templates/index.html
oteltest/viz/templates/trace.html
oteltest-0.44.0.dist-info/METADATA
oteltest-0.44.0.dist-info/WHEEL
oteltest-0.44.0.dist-info/entry_points.txt
oteltest-0.44.0.dist-info/RECORD
