Metadata-Version: 2.4
Name: oteltest
Version: 0.44.0
Summary: OpenTelemetry Tester
Project-URL: Documentation, https://github.com/pmcollins/oteltest/
Project-URL: Issues, https://github.com/pmcollins/oteltest/issues
Project-URL: Source, https://github.com/pmcollins/oteltest/blob/main/oteltest
Classifier: Development Status :: 4 - Beta
Classifier: Intended Audience :: Developers
Classifier: License :: OSI Approved :: Apache Software License
Classifier: Programming Language :: Python
Classifier: Programming Language :: Python :: 3
Classifier: Programming Language :: Python :: 3.8
Classifier: Programming Language :: Python :: 3.9
Classifier: Programming Language :: Python :: 3.10
Classifier: Programming Language :: Python :: 3.11
Classifier: Typing :: Typed
Requires-Python: >=3.8
Requires-Dist: flask
Requires-Dist: grpcio
Requires-Dist: opentelemetry-api
Requires-Dist: opentelemetry-proto
Requires-Dist: protobuf
